{
  "event": {
    "requestContext": {
      "routeKey": "sendmessage",
      "messageId": "AVKFSed-PHcCGVQ=",
      "eventType": "MESSAGE",
      "extendedRequestId": "AVKFSHS7vHcFWPw=",
      "requestTime": "14/Feb/2023:13:18:25 +0000",
      "messageDirection": "IN",
      "stage": "2022-11-22",
      "connectedAt": 1676378263853,
      "requestTimeEpoch": 1676380705521,
      "identity": {
        "userAgent": "Mozilla/5.0 (X11; Linux x86_64) AppleWebKit/537.36 (KHTML, like Gecko) Chrome/110.0.0.0 Safari/537.36",
        "sourceIp": "88.88.113.98"
      },
      "requestId": "AVKFSHS7vHcFWPw=",
      "domainName": "gqhubutcb1.execute-api.us-west-2.amazonaws.com",
      "connectionId": "AVEHxernvHcCGVQ=",
      "apiId": "gqhubutcb1"
    },
    "body": "{\"message\":\"sendmessage\",\"data\":{\"desired\":{\"led\":{\"v\":{\"color\":[0,255,0]}}},\"deviceId\":\"1078800338:demo5Gmesh_gw01\",\"code\":\"8je7dlvr\"}}",
    "isBase64Encoded": false
  }
}
